parallm/__init__.py
parallm/__main__.py
parallm/bedrock_query.py
parallm/cli.py
parallm/gemini_query.py
parallm/model_query.py
parallm/rag/__init__.py
parallm/rag/chunking.py
parallm/rag/config.py
parallm/rag/embedding.py
parallm/rag/indexing.py
parallm/rag/ingestion.py
parallm/rag/pipeline.py
parallm/rag/retrieval.py
parallm/rag/storage.py
parallm-0.2.5.dist-info/METADATA
parallm-0.2.5.dist-info/WHEEL
parallm-0.2.5.dist-info/entry_points.txt
parallm-0.2.5.dist-info/top_level.txt
parallm-0.2.5.dist-info/RECORD
