Metadata-Version: 2.4
Name: parallm
Version: 0.2.5
Summary: CLI tool for querying multiple models with prompts from a CSV with schema support
Author-email: Rohit Krishnan <rohit.krishnan@gmail.com>
License:                                  Apache License
Project-URL: Homepage, https://github.com/strangeloopcanon/parallm
Requires-Python: >=3.9
Requires-Dist: bodo
Requires-Dist: llm>=0.23
Requires-Dist: pandas
Requires-Dist: python-dotenv
Requires-Dist: pydantic>=2.0
